eveapi2/response.py
eveapi2/exceptions.py
eveapi2/utils.py
eveapi2/__init__.py
eveapi2/mixins.py
eveapi2/misc/__init__.py
eveapi2/models/alliance.py
eveapi2/models/call.py
eveapi2/models/call_group.py
eveapi2/models/character.py
eveapi2/models/__init__.py
eveapi2/models/account_status.py
eveapi2/models/server_status.py
eveapi2/models/api_key_info.py
eveapi2/models/employment_history.py
eveapi2/api/call_list.py
eveapi2/api/__init__.py
eveapi2/tests/test_mixins.py
eveapi2/tests/test_utils.py
eveapi2/tests/conftest.py
eveapi2/tests/test_api_key_info.py
eveapi2/tests/test_character_id.py
eveapi2/tests/test_account_status.py
eveapi2/tests/test_call_list.py
eveapi2/tests/test_response.py
eveapi2/tests/test_alliance.py
eveapi2/tests/test_characters.py
eveapi2/tests/test_exceptions.py
eveapi2/tests/test_character_affiliation.py
eveapi2/tests/__init__.py
eveapi2/tests/test_server_status.py
eveapi2/eve/character_affiliation.py
eveapi2/eve/__init__.py
eveapi2/eve/character_id.py
eveapi2/eve/alliance_list.py
eveapi2/server/__init__.py
eveapi2/server/server_status.py
eveapi2/character/__init__.py
eveapi2/corporation/__init__.py
eveapi2/map/__init__.py
eveapi2/account/characters.py
eveapi2/account/__init__.py
eveapi2/account/account_status.py
eveapi2/account/api_key_info.py
eveapi2-0.1.3.dist-info/RECORD
eveapi2-0.1.3.dist-info/metadata.json
eveapi2-0.1.3.dist-info/top_level.txt
eveapi2-0.1.3.dist-info/METADATA
eveapi2-0.1.3.dist-info/WHEEL
eveapi2-0.1.3.dist-info/DESCRIPTION.rst
