Metadata-Version: 2.0
Name: eveapi2
Version: 0.1.3
Summary: Sane EVE Online API
Home-page: https://github.com/lunemec/eveapi2
Author: Lukas Nemec
Author-email: lu.nemec@gmail.com
License: see LICENSE.txt
Platform: any
Classifier: Operating System :: OS Independent
Classifier: Programming Language :: Python
Classifier: Programming Language :: Python :: 3.2
Classifier: Programming Language :: Python :: 3.3
Classifier: Programming Language :: Python :: 3.4
Classifier: Topic :: Games/Entertainment
Provides: eveapi2
Provides: eveapi2.misc
Provides: eveapi2.models
Provides: eveapi2.api
Provides: eveapi2.tests
Provides: eveapi2.eve
Provides: eveapi2.server
Provides: eveapi2.character
Provides: eveapi2.corporation
Provides: eveapi2.map
Provides: eveapi2.account
Requires-Dist: beautifulsoup4
Requires-Dist: lxml
Requires-Dist: pytz
Requires-Dist: pytest
